maestral_gui/__init__.py
maestral_gui-0.1.dist-info/LICENSE.txt
maestral_gui-0.1.dist-info/METADATA
maestral_gui-0.1.dist-info/WHEEL
maestral_gui-0.1.dist-info/top_level.txt
maestral_gui-0.1.dist-info/zip-safe
maestral_gui-0.1.dist-info/RECORD
