Metadata-Version: 2.1
Name: maestral-gui
Version: 0.1
Summary: Open-source Dropbox client for macOS and Linux.
Home-page: https://github.com/SamSchott/maestral-gui
Author: Sam Schott
Author-email: ss2151@cam.ac.uk
License: MIT
Platform: UNKNOWN
Classifier: License :: OSI Approved :: MIT License
Classifier: Operating System :: MacOS
Classifier: Programming Language :: Python
Classifier: Programming Language :: Python :: 3
Classifier: Programming Language :: Python :: 3.6
Classifier: Programming Language :: Python :: 3.7
Classifier: Programming Language :: Python :: 3.8
Classifier: Programming Language :: Python :: 3 :: Only
Requires-Python: >=3.6
Requires-Dist: maestral-cocoa (>=1.2.1) ; sys_platform == "darwin"
Requires-Dist: maestral-qt (>=1.2.1) ; sys_platform == "linux"
